dc_event_logs_mcp_client/__init__.py
dc_event_logs_mcp_client/client.py
itarundaniel_dc_event_logs_mcp_client-1.0.1.dist-info/licenses/LICENSE
itarundaniel_dc_event_logs_mcp_client-1.0.1.dist-info/METADATA
itarundaniel_dc_event_logs_mcp_client-1.0.1.dist-info/WHEEL
itarundaniel_dc_event_logs_mcp_client-1.0.1.dist-info/entry_points.txt
itarundaniel_dc_event_logs_mcp_client-1.0.1.dist-info/top_level.txt
itarundaniel_dc_event_logs_mcp_client-1.0.1.dist-info/RECORD
