Metadata-Version: 2.4
Name: itarundaniel-dc-event-logs-mcp-client
Version: 1.0.1
Summary: MCP client proxy for querying Windows Domain Controller Event Logs
Author-email: Arun Daniel <itarundaniel@gmail.com>
License: MIT
Keywords: mcp,windows,event-logs,domain-controller,active-directory
Classifier: Development Status :: 4 - Beta
Classifier: Intended Audience :: System Administrators
Classifier: Topic :: System :: Systems Administration
Classifier: License :: OSI Approved :: MIT License
Classifier: Programming Language :: Python :: 3
Classifier: Programming Language :: Python :: 3.9
Classifier: Programming Language :: Python :: 3.10
Classifier: Programming Language :: Python :: 3.11
Classifier: Programming Language :: Python :: 3.12
Classifier: Programming Language :: Python :: 3.13
Classifier: Operating System :: Microsoft :: Windows
Requires-Python: >=3.9
License-File: LICENSE
Requires-Dist: mcp>=0.9.0
Dynamic: license-file
